allan_variance/__init__.py
allan_variance/avar.py
allan_variance/noise.py
allan_variance/tests/test_avar.py
allan_variance/tests/test_noise.py
allan_variance-1.0.dist-info/LICENSE.txt
allan_variance-1.0.dist-info/METADATA
allan_variance-1.0.dist-info/WHEEL
allan_variance-1.0.dist-info/top_level.txt
allan_variance-1.0.dist-info/RECORD
