Metadata-Version: 2.1
Name: allan-variance
Version: 1.0
Summary: Allan variance and noise parameter estimation
Maintainer-email: Nikolay Mayorov <nikolay.mayorov@zoho.com>
License: MIT License
Project-URL: Homepage, https://github.com/nmayorov/allan-variance
Keywords: Allan Variance,Estimation,Noise
Classifier: Development Status :: 5 - Production/Stable
Classifier: Intended Audience :: Developers
Classifier: Intended Audience :: Science/Research
Classifier: Topic :: Scientific/Engineering
Classifier: License :: OSI Approved :: MIT License
Classifier: Programming Language :: Python :: 3
License-File: LICENSE.txt
Requires-Dist: numpy
Requires-Dist: scipy
Requires-Dist: pandas
